h5sh/__init__.py
h5sh/__main__.py
h5sh/console.py
h5sh/state.py
h5sh/styles.py
h5sh/utils.py
h5sh/commands/__init__.py
h5sh/commands/base.py
h5sh/commands/miniargparse.py
h5sh/commands/navigation.py
h5sh/commands/query.py
h5sh/commands/registry.py
h5sh/commands/system.py
h5sh/scripts/__init__.py
h5sh/scripts/main.py
h5sh-0.1.1.dist-info/DESCRIPTION.rst
h5sh-0.1.1.dist-info/METADATA
h5sh-0.1.1.dist-info/RECORD
h5sh-0.1.1.dist-info/WHEEL
h5sh-0.1.1.dist-info/entry_points.txt
h5sh-0.1.1.dist-info/metadata.json
h5sh-0.1.1.dist-info/top_level.txt
