Metadata-Version: 2.0
Name: h5sh
Version: 0.1.1
Summary: Fast shell-like tool for interacting with HDF5 files.
Home-page: https://github.com/sethrj/h5sh
Author: Seth Robert Johnson
Author-email: johnsonsr@ornl.gov
License: BSD license
Keywords: h5sh
Platform: UNKNOWN
Classifier: Development Status :: 2 - Pre-Alpha
Classifier: Intended Audience :: Developers
Classifier: License :: OSI Approved :: BSD License
Classifier: Natural Language :: English
Classifier: Programming Language :: Python :: 2
Classifier: Programming Language :: Python :: 2.7
Classifier: Programming Language :: Python :: 3
Classifier: Programming Language :: Python :: 3.4
Classifier: Programming Language :: Python :: 3.5
Classifier: Programming Language :: Python :: 3.6
Classifier: Programming Language :: Python :: 3.7
Requires-Dist: h5py (>=2.7.1)
Requires-Dist: prompt-toolkit (>=2.0)
Requires-Dist: numpy (>=1.15)
Requires-Dist: pygments
Requires-Dist: six
